Workbook

Sheet Synthese
A1: Suivi SEO du projet
A2: Cellules jaunes : à compléter. Le reste se calcule tout seul.
A3: Projet / client | C3: Exemple : ducoinweb.fr
A4: URL du site | C4: Exemple : https://ducoinweb.fr/
A5: Date de début | C5: Exemple : 15/10/2026
A6: Formule vendue | C6: Essentiel = niveau de base. Complet = base + renforcé.
A8: Avancement
A9: Niveau | B9: Tâches | C9: Faites | D9: Avancement
A10: Base | B10: =COUNTIFS(Checklist!$B$2:$B$120,"Base",Checklist!$E$2:$E$120,"<>Non applicable") -> 41 | C10: =COUNTIFS(Checklist!$B$2:$B$120,"Base",Checklist!$E$2:$E$120,"Fait") -> 0 | D10: =IF(B10=0,"",C10/B10) -> 0
A11: Renforcé | B11: =IF($B$6="Essentiel","Non inclus",COUNTIFS(Checklist!$B$2:$B$120,"Renforcé",Checklist!$E$2:$E$120,"<>Non applicable")) -> 16 | C11: =IF($B$6="Essentiel","",COUNTIFS(Checklist!$B$2:$B$120,"Renforcé",Checklist!$E$2:$E$120,"Fait")) -> 0 | D11: =IF($B$6="Essentiel","Non inclus",IF(B11=0,"",C11/B11)) -> 0
A12: Total | B12: =B10+IF($B$6="Essentiel",0,B11) -> 57 | C12: =C10+IF($B$6="Essentiel",0,C11) -> 0 | D12: =IF(B12=0,"",C12/B12) -> 0
A14: Prochaine tâche | B14: =IF(MIN(Checklist!$H$2:$H$120)=0,"Tout est fait",INDEX(Checklist!$D$1:$D$120,MIN(Checklist!$H$2:$H$120))) -> Le site répond en HTTPS, et http:// redirige vers https://
A16: Avancement par catégorie
A17: Catégorie | B17: Niveau | C17: Tâches | D17: Faites | E17: Avancement
A18: Indexation et technique | B18: Base | C18: =IF(AND(B18="Renforcé",$B$6="Essentiel"),"Non inclus",COUNTIFS(Checklist!$C$2:$C$120,A18,Checklist!$E$2:$E$120,"<>Non applicable")) -> 9 | D18: =IF(AND(B18="Renforcé",$B$6="Essentiel"),"",COUNTIFS(Checklist!$C$2:$C$120,A18,Checklist!$E$2:$E$120,"Fait")) -> 0 | E18: =IF(AND(B18="Renforcé",$B$6="Essentiel"),"Non inclus",IF(C18=0,"",D18/C18)) -> 0
A19: Balises de chaque page | B19: Base | C19: =IF(AND(B19="Renforcé",$B$6="Essentiel"),"Non inclus",COUNTIFS(Checklist!$C$2:$C$120,A19,Checklist!$E$2:$E$120,"<>Non applicable")) -> 6 | D19: =IF(AND(B19="Renforcé",$B$6="Essentiel"),"",COUNTIFS(Checklist!$C$2:$C$120,A19,Checklist!$E$2:$E$120,"Fait")) -> 0 | E19: =IF(AND(B19="Renforcé",$B$6="Essentiel"),"Non inclus",IF(C19=0,"",D19/C19)) -> 0
A20: Contenu | B20: Base | C20: =IF(AND(B20="Renforcé",$B$6="Essentiel"),"Non inclus",COUNTIFS(Checklist!$C$2:$C$120,A20,Checklist!$E$2:$E$120,"<>Non applicable")) -> 5 | D20: =IF(AND(B20="Renforcé",$B$6="Essentiel"),"",COUNTIFS(Checklist!$C$2:$C$120,A20,Checklist!$E$2:$E$120,"Fait")) -> 0 | E20: =IF(AND(B20="Renforcé",$B$6="Essentiel"),"Non inclus",IF(C20=0,"",D20/C20)) -> 0
A21: Liens | B21: Base | C21: =IF(AND(B21="Renforcé",$B$6="Essentiel"),"Non inclus",COUNTIFS(Checklist!$C$2:$C$120,A21,Checklist!$E$2:$E$120,"<>Non applicable")) -> 5 | D21: =IF(AND(B21="Renforcé",$B$6="Essentiel"),"",COUNTIFS(Checklist!$C$2:$C$120,A21,Checklist!$E$2:$E$120,"Fait")) -> 0 | E21: =IF(AND(B21="Renforcé",$B$6="Essentiel"),"Non inclus",IF(C21=0,"",D21/C21)) -> 0
A22: Images | B22: Base | C22: =IF(AND(B22="Renforcé",$B$6="Essentiel"),"Non inclus",COUNTIFS(Checklist!$C$2:$C$120,A22,Checklist!$E$2:$E$120,"<>Non applicable")) -> 6 | D22: =IF(AND(B22="Renforcé",$B$6="Essentiel"),"",COUNTIFS(Checklist!$C$2:$C$120,A22,Checklist!$E$2:$E$120,"Fait")) -> 0 | E22: =IF(AND(B22="Renforcé",$B$6="Essentiel"),"Non inclus",IF(C22=0,"",D22/C22)) -> 0
A23: Performance et mobile | B23: Base | C23: =IF(AND(B23="Renforcé",$B$6="Essentiel"),"Non inclus",COUNTIFS(Checklist!$C$2:$C$120,A23,Checklist!$E$2:$E$120,"<>Non applicable")) -> 5 | D23: =IF(AND(B23="Renforcé",$B$6="Essentiel"),"",COUNTIFS(Checklist!$C$2:$C$120,A23,Checklist!$E$2:$E$120,"Fait")) -> 0 | E23: =IF(AND(B23="Renforcé",$B$6="Essentiel"),"Non inclus",IF(C23=0,"",D23/C23)) -> 0
A24: Google | B24: Base | C24: =IF(AND(B24="Renforcé",$B$6="Essentiel"),"Non inclus",COUNTIFS(Checklist!$C$2:$C$120,A24,Checklist!$E$2:$E$120,"<>Non applicable")) -> 5 | D24: =IF(AND(B24="Renforcé",$B$6="Essentiel"),"",COUNTIFS(Checklist!$C$2:$C$120,A24,Checklist!$E$2:$E$120,"Fait")) -> 0 | E24: =IF(AND(B24="Renforcé",$B$6="Essentiel"),"Non inclus",IF(C24=0,"",D24/C24)) -> 0
A25: Fiche Google Business Profile | B25: Renforcé | C25: =IF(AND(B25="Renforcé",$B$6="Essentiel"),"Non inclus",COUNTIFS(Checklist!$C$2:$C$120,A25,Checklist!$E$2:$E$120,"<>Non applicable")) -> 7 | D25: =IF(AND(B25="Renforcé",$B$6="Essentiel"),"",COUNTIFS(Checklist!$C$2:$C$120,A25,Checklist!$E$2:$E$120,"Fait")) -> 0 | E25: =IF(AND(B25="Renforcé",$B$6="Essentiel"),"Non inclus",IF(C25=0,"",D25/C25)) -> 0
A26: Cohérence des informations | B26: Renforcé | C26: =IF(AND(B26="Renforcé",$B$6="Essentiel"),"Non inclus",COUNTIFS(Checklist!$C$2:$C$120,A26,Checklist!$E$2:$E$120,"<>Non applicable")) -> 3 | D26: =IF(AND(B26="Renforcé",$B$6="Essentiel"),"",COUNTIFS(Checklist!$C$2:$C$120,A26,Checklist!$E$2:$E$120,"Fait")) -> 0 | E26: =IF(AND(B26="Renforcé",$B$6="Essentiel"),"Non inclus",IF(C26=0,"",D26/C26)) -> 0
A27: Présence locale | B27: Renforcé | C27: =IF(AND(B27="Renforcé",$B$6="Essentiel"),"Non inclus",COUNTIFS(Checklist!$C$2:$C$120,A27,Checklist!$E$2:$E$120,"<>Non applicable")) -> 3 | D27: =IF(AND(B27="Renforcé",$B$6="Essentiel"),"",COUNTIFS(Checklist!$C$2:$C$120,A27,Checklist!$E$2:$E$120,"Fait")) -> 0 | E27: =IF(AND(B27="Renforcé",$B$6="Essentiel"),"Non inclus",IF(C27=0,"",D27/C27)) -> 0
A28: Galerie photo | B28: Renforcé | C28: =IF(AND(B28="Renforcé",$B$6="Essentiel"),"Non inclus",COUNTIFS(Checklist!$C$2:$C$120,A28,Checklist!$E$2:$E$120,"<>Non applicable")) -> 1 | D28: =IF(AND(B28="Renforcé",$B$6="Essentiel"),"",COUNTIFS(Checklist!$C$2:$C$120,A28,Checklist!$E$2:$E$120,"Fait")) -> 0 | E28: =IF(AND(B28="Renforcé",$B$6="Essentiel"),"Non inclus",IF(C28=0,"",D28/C28)) -> 0
A29: Suivi | B29: Renforcé | C29: =IF(AND(B29="Renforcé",$B$6="Essentiel"),"Non inclus",COUNTIFS(Checklist!$C$2:$C$120,A29,Checklist!$E$2:$E$120,"<>Non applicable")) -> 2 | D29: =IF(AND(B29="Renforcé",$B$6="Essentiel"),"",COUNTIFS(Checklist!$C$2:$C$120,A29,Checklist!$E$2:$E$120,"Fait")) -> 0 | E29: =IF(AND(B29="Renforcé",$B$6="Essentiel"),"Non inclus",IF(C29=0,"",D29/C29)) -> 0
A31: Mode d'emploi
A32: Onglet Checklist : choisir un statut dans la liste de la colonne E, saisir la date en F, noter les remarques en G.
A33: Les lignes vides de la Checklist (jusqu'à la ligne 120) servent à ajouter des tâches propres au projet. Renseigner le niveau (Base ou Renforcé), la catégorie et la tâche.
A34: Onglet Pages : une ligne par page du site. Copier le title et la meta description, la longueur se calcule seule.
A35: La colonne H de la Checklist est masquée : elle sert à calculer la prochaine tâche. Ne pas la supprimer.
A36: La ligne d'exemple de l'onglet Pages (Tarifs) est à remplacer par les pages du projet.

Sheet Checklist
A1: N° | B1: Niveau | C1: Catégorie | D1: Tâche | E1: Statut | F1: Date | G1: Notes | H1: Ordre
A2: 1 | B2: Base | C2: Indexation et technique | D2: Le site répond en HTTPS, et http:// redirige vers https:// | E2: À faire | H2: =IF(OR(E2="Fait",E2="Non applicable",D2=""),"",IF(AND(B2="Renforcé",Synthese!$B$6="Essentiel"),"",ROW())) -> 2
A3: 2 | B3: Base | C3: Indexation et technique | D3: robots.txt présent, sans Disallow sur les pages utiles, avec l'URL du sitemap | E3: À faire | H3: =IF(OR(E3="Fait",E3="Non applicable",D3=""),"",IF(AND(B3="Renforcé",Synthese!$B$6="Essentiel"),"",ROW())) -> 3
A4: 3 | B4: Base | C4: Indexation et technique | D4: sitemap.xml présent, avec uniquement des URLs qui répondent en 200 (pas de 404, pas de redirection) | E4: À faire | H4: =IF(OR(E4="Fait",E4="Non applicable",D4=""),"",IF(AND(B4="Renforcé",Synthese!$B$6="Essentiel"),"",ROW())) -> 4
A5: 4 | B5: Base | C5: Indexation et technique | D5: URLs du sitemap identiques aux URLs canoniques (sans .html si le site les redirige) | E5: À faire | H5: =IF(OR(E5="Fait",E5="Non applicable",D5=""),"",IF(AND(B5="Renforcé",Synthese!$B$6="Essentiel"),"",ROW())) -> 5
A6: 5 | B6: Base | C6: Indexation et technique | D6: Une balise canonical par page, qui pointe vers elle-même | E6: À faire | H6: =IF(OR(E6="Fait",E6="Non applicable",D6=""),"",IF(AND(B6="Renforcé",Synthese!$B$6="Essentiel"),"",ROW())) -> 6
A7: 6 | B7: Base | C7: Indexation et technique | D7: Aucune URL en double : /index.html redirige vers /, les .html vers l'URL sans extension | E7: À faire | H7: =IF(OR(E7="Fait",E7="Non applicable",D7=""),"",IF(AND(B7="Renforcé",Synthese!$B$6="Essentiel"),"",ROW())) -> 7
A8: 7 | B8: Base | C8: Indexation et technique | D8: Page 404 personnalisée en noindex | E8: À faire | H8: =IF(OR(E8="Fait",E8="Non applicable",D8=""),"",IF(AND(B8="Renforcé",Synthese!$B$6="Essentiel"),"",ROW())) -> 8
A9: 8 | B9: Base | C9: Indexation et technique | D9: Slugs courts, en minuscules, avec des tirets, sans accent ni espace | E9: À faire | H9: =IF(OR(E9="Fait",E9="Non applicable",D9=""),"",IF(AND(B9="Renforcé",Synthese!$B$6="Essentiel"),"",ROW())) -> 9
A10: 9 | B10: Base | C10: Indexation et technique | D10: Redirection 301 pour chaque URL renommée ou supprimée | E10: À faire | H10: =IF(OR(E10="Fait",E10="Non applicable",D10=""),"",IF(AND(B10="Renforcé",Synthese!$B$6="Essentiel"),"",ROW())) -> 10
A11: 10 | B11: Base | C11: Balises de chaque page | D11: title unique, 60 caractères maximum, mot-clé principal au début | E11: À faire | H11: =IF(OR(E11="Fait",E11="Non applicable",D11=""),"",IF(AND(B11="Renforcé",Synthese!$B$6="Essentiel"),"",ROW())) -> 11
A12: 11 | B12: Base | C12: Balises de chaque page | D12: meta description unique, entre 100 et 155 caractères, avec une promesse concrète (délai, prix) | E12: À faire | H12: =IF(OR(E12="Fait",E12="Non applicable",D12=""),"",IF(AND(B12="Renforcé",Synthese!$B$6="Essentiel"),"",ROW())) -> 12
A13: 12 | B13: Base | C13: Balises de chaque page | D13: Pas de meta keywords (ignorée par Google) | E13: À faire | H13: =IF(OR(E13="Fait",E13="Non applicable",D13=""),"",IF(AND(B13="Renforcé",Synthese!$B$6="Essentiel"),"",ROW())) -> 13
... A58: 57 | B58: Renforcé | C58: Suivi | D58: Contrôle des requêtes et des clics à 30 jours, partagé avec le client | E58: À faire | H58: =IF(OR(E58="Fait",E58="Non applicable",D58=""),"",IF(AND(B58="Renforcé",Synthese!$B$6="Essentiel"),"",ROW())) -> 58
H59: =IF(OR(E59="Fait",E59="Non applicable",D59=""),"",IF(AND(B59="Renforcé",Synthese!$B$6="Essentiel"),"",ROW()))
H60: =IF(OR(E60="Fait",E60="Non applicable",D60=""),"",IF(AND(B60="Renforcé",Synthese!$B$6="Essentiel"),"",ROW()))
H61: =IF(OR(E61="Fait",E61="Non applicable",D61=""),"",IF(AND(B61="Renforcé",Synthese!$B$6="Essentiel"),"",ROW()))
H62: =IF(OR(E62="Fait",E62="Non applicable",D62=""),"",IF(AND(B62="Renforcé",Synthese!$B$6="Essentiel"),"",ROW()))
H63: =IF(OR(E63="Fait",E63="Non applicable",D63=""),"",IF(AND(B63="Renforcé",Synthese!$B$6="Essentiel"),"",ROW()))
H64: =IF(OR(E64="Fait",E64="Non applicable",D64=""),"",IF(AND(B64="Renforcé",Synthese!$B$6="Essentiel"),"",ROW()))
H65: =IF(OR(E65="Fait",E65="Non applicable",D65=""),"",IF(AND(B65="Renforcé",Synthese!$B$6="Essentiel"),"",ROW()))
H66: =IF(OR(E66="Fait",E66="Non applicable",D66=""),"",IF(AND(B66="Renforcé",Synthese!$B$6="Essentiel"),"",ROW()))
H67: =IF(OR(E67="Fait",E67="Non applicable",D67=""),"",IF(AND(B67="Renforcé",Synthese!$B$6="Essentiel"),"",ROW()))
H68: =IF(OR(E68="Fait",E68="Non applicable",D68=""),"",IF(AND(B68="Renforcé",Synthese!$B$6="Essentiel"),"",ROW()))
H69: =IF(OR(E69="Fait",E69="Non applicable",D69=""),"",IF(AND(B69="Renforcé",Synthese!$B$6="Essentiel"),"",ROW()))
H70: =IF(OR(E70="Fait",E70="Non applicable",D70=""),"",IF(AND(B70="Renforcé",Synthese!$B$6="Essentiel"),"",ROW()))
... H120: =IF(OR(E120="Fait",E120="Non applicable",D120=""),"",IF(AND(B120="Renforcé",Synthese!$B$6="Essentiel"),"",ROW()))

Sheet Pages
A1: Page | B1: URL | C1: Title | D1: Long. title | E1: Meta description | F1: Long. description | G1: H1 unique | H1: Alt sur images | I1: og:image | J1: Dans le sitemap | K1: Indexée (Search Console) | L1: Date de contrôle | M1: Notes
A2: Tarifs | B2: https://ducoinweb.fr/tarifs | C2: Création de site vitrine : 900 € ou 1 600 € | P-A Ducoin | D2: =IF(C2="","",LEN(C2)) -> 56 | E2: Deux formules à prix fixe : Essentiel à 900 € et Complet à 1 600 €. Contenu de chaque formule, options, retouches et paiement. | F2: =IF(E2="","",LEN(E2)) -> 126 | G2: Oui | H2: Oui | I2: Oui | J2: Oui | K2: À vérifier | L2: 46310 | M2: Exemple à remplacer par les pages du projet
D3: =IF(C3="","",LEN(C3)) | F3: =IF(E3="","",LEN(E3))
D4: =IF(C4="","",LEN(C4)) | F4: =IF(E4="","",LEN(E4))
D5: =IF(C5="","",LEN(C5)) | F5: =IF(E5="","",LEN(E5))
D6: =IF(C6="","",LEN(C6)) | F6: =IF(E6="","",LEN(E6))
D7: =IF(C7="","",LEN(C7)) | F7: =IF(E7="","",LEN(E7))
D8: =IF(C8="","",LEN(C8)) | F8: =IF(E8="","",LEN(E8))
D9: =IF(C9="","",LEN(C9)) | F9: =IF(E9="","",LEN(E9))
D10: =IF(C10="","",LEN(C10)) | F10: =IF(E10="","",LEN(E10))
D11: =IF(C11="","",LEN(C11)) | F11: =IF(E11="","",LEN(E11))
D12: =IF(C12="","",LEN(C12)) | F12: =IF(E12="","",LEN(E12))
D13: =IF(C13="","",LEN(C13)) | F13: =IF(E13="","",LEN(E13))
D14: =IF(C14="","",LEN(C14)) | F14: =IF(E14="","",LEN(E14))
... D40: =IF(C40="","",LEN(C40)) | F40: =IF(E40="","",LEN(E40))
A42: Title : 60 caractères maximum (rouge au-delà). Meta description : entre 100 et 155 caractères (rouge sinon).
